[
  {
    "Title": "Highjacked Season 01",
    "audio": "https://hearthis.at/djg400/dj-g400-highjacked-season-01-audio/listen.mp3?s=C6f",
    "Album": "Highjacked",
    "Episode": 1,
    "color": "#ffcc33",
    "hue": "",
    "popular": 1,
    "Genre": "Trap",
    "Artists": "Rae Sremmurd, Young Dolph, Kent, jones, Madeintyo",
    "Cover": "./cover/hs01.jpg",
    "thumbnail": "./image/mix-covers/thumbnail/hs01.jpg",
    "thumbnailLg": "",
    "id": "2",
    "similar": "1, 6, 10, 14, 17, 23, 24, ",
    "date": "23 Dec 2016",
    "tracklist": ""
  },
  {
    "Title": "Highjacked Season 02",
    "audio": "https://hearthis.at/djg400/dj-g400-highjacked-season-02-audio./listen.mp3?s=etS",
    "Album": "Highjacked",
    "Episode": 2,
    "color": "#e71f35",
    "hue": "",
    "popular": 2,
    "Genre": "Trap",
    "Artists": "MGK, Ty Dolla $ign, Future, 2 Chainz, 21 Savage",
    "Cover": "./cover/hs02.jpg",
    "thumbnail": "./image/mix-covers/thumbnail/hs02.jpg",
    "thumbnailLg": "./image/mix-covers/djg400-bg-lg.jpg",
    "id": "6",
    "similar": "1, 6, 10, 14, 17, 23, 24, ",
    "date": "13 Mar 2017",
    "tracklist": ""
  },
  {
    "Title": "Highjacked Season 03",
    "audio": "https://hearthis.at/djg400/dj-g400-highjacked-season-03-audio/listen.mp3?s=LrQ",
    "Album": "Highjacked",
    "Episode": 3,
    "color": "#ff1912",
    "hue": "",
    "popular": 3,
    "Genre": "Trap, Hip Hop, Rap",
    "Artists": "Big Sean, Kodack Black, Ayo & Teo, Migos, PnB Rock",
    "Cover": "./cover/hs03.jpg",
    "thumbnail": "./image/mix-covers/thumbnail/hs03.jpg",
    "thumbnailLg": "./image/mix-covers/highjacked-03-lg.jpg",
    "id": "10",
    "similar": "1, 6, 10, 14, 17, 23, 24, ",
    "date": "12 Aug 2017",
    "tracklist": ""
  },
  {
    "Title": "Highjacked Season 04",
    "audio": "https://hearthis.at/djg400/dj-g400-highjacked-season-04-audio/listen.mp3?s=NGb",
    "Album": "Highjacked",
    "Episode": 4,
    "color": "#d4ff06",
    "hue": "",
    "popular": 4,
    "Genre": "Trap, Hip Hop, Rap",
    "Artists": "Lil Pump, Moneybag Yo, Lil Yatchy, Nicki Minaj, Konshens, Tyga",
    "Cover": "./cover/hs04.jpg",
    "thumbnail": "./image/mix-covers/thumbnail/hs04.jpg",
    "thumbnailLg": "./image/mix-covers/djg400-bg-lg.jpg",
    "id": "14",
    "similar": "1, 6, 10, 14, 17, 23, 24, ",
    "date": "09 Jul 2018",
    "tracklist": ""
  },
  {
    "Title": "Highjacked Season 05",
    "audio": "https://hearthis.at/djg400/dj-g400-highjacked-season-05-audio/listen.mp3?s=6zE",
    "Album": "Highjacked",
    "Episode": 5,
    "color": "#00fe60",
    "hue": "",
    "popular": 5,
    "Genre": "Trap, Hip Hop, Rap",
    "Artists": "French Montana, Tory Lanez, Lil Mosey, Rich The Kid, Juice Wrld, Childish Gambino",
    "Cover": "./cover/hs05.jpg",
    "thumbnail": "./image/mix-covers/thumbnail/hs05.jpg",
    "thumbnailLg": "./image/mix-covers/djg400-bg-lg.jpg",
    "id": "17",
    "similar": "1, 6, 10, 14, 17, 23, 24, ",
    "date": "30 Dec 2018",
    "tracklist": ""
  },
  {
    "Title": "Highjacked Season 06",
    "audio": "https://hearthis.at/djg400/dj-g400-highjacked-season-06-audio/listen.mp3?s=cBE",
    "Album": "Highjacked",
    "Episode": 6,
    "color": "#dedede",
    "hue": "",
    "popular": 5,
    "Genre": "Trap, Hip Hop, Rap",
    "Artists": "Gucci Mane, Key Glock, Young Dolph, Travis Scott, Khaligraph Jones, Smokepurpp, YNW Melly, YG",
    "Cover": "./cover/hs06.jpg",
    "thumbnail": "./image/mix-covers/thumbnail/hs06.jpg",
    "thumbnailLg": "./image/mix-covers/djg400-bg-lg.jpg",
    "id": "23",
    "similar": "1, 6, 10, 14, 17, 23, 24, ",
    "date": "25 Oct 2019",
    "tracklist": ""
  },
  {
    "Title": "Highjacked Season 07",
    "audio": "https://hearthis.at/djg400/dj-g400-highjacked-season-07-auido/listen.mp3?s=lge",
    "Album": "Highjacked",
    "Episode": 7,
    "color": "#fcbb30",
    "hue": "filter: hue-rotate(220deg);",
    "popular": 7,
    "Genre": "Trap, Hip Hop, Rap",
    "Artists": "Roddy Ricch, NAV, Gunna, Sheck Wes, Don Toliver,Yo Gotti, Megan Thee Stallion, Lil Uzi Vert",
    "Cover": "./cover/hs07.jpg",
    "thumbnail": "./image/mix-covers/thumbnail/hs07.jpg",
    "thumbnailLg": "./image/mix-covers/highjacked-07-lg.jpg",
    "id": "24",
    "similar": "1, 6, 10, 14, 17, 23, 24, ",
    "date": "04 May 2020",
    "tracklist": ""
  },
  {
    "Title": "Highjacked Season 08",
    "audio": "https://hearthis.at/djg400/dj-g400-highjacked-season-07-auido/listen.mp3?s=lge",
    "Album": "Highjacked",
    "Episode": 8,
    "color": "#fcbb30",
    "hue": "filter: hue-rotate(220deg);",
    "popular": 5,
    "Genre": "Trap",
    "Artists": "Gunna, Don Toliver,Yo Gotti, Megan Thee Stallion, Lil Uzi Vert, Pop Smoke, Skepta, Dave, Lil Skies, Wiz Khalifa, Young Dolph, Key Glock, Snupe Bandz, Big Moochie Grape, Jay Fizzle, PaperRoute Woo, Lil Baby, Big Uncc",
    "Cover": "./cover/hs08.jpg",
    "thumbnail": "./image/mix-covers/thumbnail/hs08.jpg",
    "thumbnailLg": "./image/mix-covers/djg400-bg-lg.jpg",
    "id": "39",
    "similar": "1, 6, 10, 14, 17, 23, 24, ",
    "date": "01 Sep 2023",
    "tracklist": ""
  },
  {
    "Title": "African Experience 01",
    "audio": "",
    "Album": "African Experience",
    "Episode": 1,
    "color": "#c57d24",
    "hue": "",
    "popular": 1,
    "Genre": "East Africa, Afrobeats",
    "Artists": "Evie Vara, Octopizzo",
    "Cover": "./cover/ae01.jpg",
    "thumbnail": "./image/mix-covers/thumbnail/ae01.jpg",
    "thumbnailLg": "",
    "id": "1",
    "date": "07 Sep 2016",
    "tracklist": ""
  },
  {
    "Title": "African Experience 02",
    "audio": "https://hearthis.at/djg400/dj-g400-an-african-experience-02-audio/listen.mp3?s=qpc",
    "Album": "African Experience",
    "Episode": 2,
    "color": "#090f50",
    "hue": "",
    "popular": 2,
    "Genre": "East Africa, Afrobeats",
    "Artists": "Sauti Sol,",
    "Cover": "./cover/ae02.jpg",
    "thumbnail": "./image/mix-covers/thumbnail/ae02.jpg",
    "thumbnailLg": "./image/mix-covers/ae02-landscape.jpg",
    "id": "4",
    "date": "04 Jan 2017",
    "tracklist": ""
  },
  {
    "Title": "African Experience 03",
    "audio": "https://hearthis.at/djg400/dj-g400-an-african-experience-03-audio./listen.mp3?s=fzq",
    "Album": "African Experience",
    "Episode": 3,
    "color": "#ecedf1",
    "hue": "",
    "popular": 3,
    "Genre": "East Africa, Afrobeats",
    "Artists": "",
    "Cover": "./cover/ae03.jpg",
    "thumbnail": "./image/mix-covers/thumbnail/ae03.jpg",
    "thumbnailLg": "./image/mix-covers/djg400-bg-lg.jpg",
    "id": "7",
    "date": "13 Mar 2017",
    "tracklist": ""
  },
  {
    "Title": "African Experience 04",
    "audio": "https://hearthis.at/djg400/dj-g400-an-african-experience-04-audio/listen.mp3?s=dwM",
    "Album": "African Experience",
    "Episode": 4,
    "color": "#a8900c",
    "hue": "",
    "popular": 2,
    "Genre": "East Africa, Afrobeats",
    "Artists": "",
    "Cover": "./cover/ae04.jpg",
    "thumbnail": "./image/mix-covers/thumbnail/ae04.jpg",
    "thumbnailLg": "./image/mix-covers/djg400-bg-lg.jpg",
    "id": "9",
    "date": "24 Jun 2017",
    "tracklist": ""
  },
  {
    "Title": "African Experience 05",
    "audio": "https://hearthis.at/djg400/dj-g400-an-african-experience-05-audio/listen.mp3?s=dzu",
    "Album": "African Experience",
    "Episode": 5,
    "color": "#fd181f",
    "hue": "",
    "popular": 5,
    "Genre": "Africa, Afro, EA",
    "Artists": "",
    "Cover": "./cover/ae05.jpg",
    "thumbnail": "./image/mix-covers/thumbnail/ae05.jpg",
    "thumbnailLg": "./image/mix-covers/djg400-bg-lg.jpg",
    "id": "12",
    "date": "18 Dec 2017",
    "tracklist": ""
  },
  {
    "Title": "African Experience 06",
    "audio": "https://hearthis.at/djg400/dj-g400-an-african-experience-06-audio/listen.mp3?s=9VZ",
    "Album": "African Experience",
    "Episode": 6,
    "color": "#eb4103",
    "hue": "",
    "popular": 2,
    "Genre": "East Africa, Afrobeats",
    "Artists": "",
    "Cover": "./cover/ae06.jpg",
    "thumbnail": "./image/mix-covers/thumbnail/ae06.jpg",
    "thumbnailLg": "./image/mix-covers/djg400-bg-lg.jpg",
    "id": "22",
    "date": "22 Sep 2019",
    "tracklist": ""
  },
  {
    "Title": "Club Inferno 01",
    "audio": "",
    "Album": "Club Inferno",
    "Episode": 1,
    "color": "#ff6d22",
    "hue": "",
    "popular": 1,
    "Genre": "Mashup, RnB, Dancehall, Hip Hop, Afro",
    "Artists": "",
    "Cover": "./cover/inferno-01.jpg",
    "thumbnail": "./image/mix-covers/thumbnail/inferno01.jpg",
    "thumbnailLg": "./image/mix-covers/djg400-bg-lg.jpg",
    "id": "3",
    "date": "03 Sep 2016",
    "tracklist": ""
  },
  {
    "Title": "Club Inferno 02",
    "audio": "https://hearthis.at/djg400/dj-g400-club-inferno-02-audio/listen.mp3?s=eya",
    "Album": "Club Inferno",
    "Episode": 2,
    "color": "#d6450e",
    "hue": "",
    "popular": 1,
    "Genre": "Mashup, RnB, Dancehall, Hip Hop, Afro",
    "Artists": "",
    "Cover": "./cover/ci01.jpg",
    "thumbnail": "./image/mix-covers/thumbnail/inferno02.jpg",
    "thumbnailLg": "./image/mix-covers/djg400-bg-lg.jpg",
    "id": "5",
    "date": "28 Jan 2017",
    "tracklist": ""
  },
  {
    "Title": "Club Inferno 03",
    "audio": "https://hearthis.at/djg400/dj-g400-club-inferno-03-audio/listen.mp3?s=YXq",
    "Album": "Club Inferno",
    "Episode": 3,
    "color": "#dcc4b0",
    "hue": "",
    "popular": 3,
    "Genre": "Mashup, RnB, Dancehall, Hip Hop, Afro",
    "Artists": "",
    "Cover": "./cover/inderno01.jpg",
    "thumbnail": "./image/mix-covers/thumbnail/inferno03.jpg",
    "thumbnailLg": "./image/mix-covers/djg400-bg-lg.jpg",
    "id": "13",
    "date": "19 Sep 2018",
    "tracklist": ""
  },
  {
    "Title": "Club Inferno 04",
    "audio": "https://hearthis.at/djg400/dj-g400-club-inferno-04-audio/listen.mp3?s=fgP",
    "Album": "Club Inferno",
    "Episode": 4,
    "color": "#ff9900",
    "hue": "",
    "popular": 4,
    "Genre": "Mashup, RnB, Dancehall, Hip Hop, Afro",
    "Artists": "",
    "Cover": "./cover/ci04.jpg",
    "thumbnail": "./image/mix-covers/thumbnail/inferno04.jpg",
    "thumbnailLg": "./image/mix-covers/djg400-bg-lg.jpg",
    "id": "20",
    "date": "27 Mar 2019",
    "tracklist": ""
  },
  {
    "Title": "Mixconduct Vol 01",
    "audio": "https://hearthis.at/djg400/dj-g400-mixconduct-vol-01-audio/listen.mp3?s=dTn",
    "Album": "Mixconduct",
    "Episode": 1,
    "color": "#efab58",
    "hue": "",
    "popular": 1,
    "Genre": "Hip Hop, Rnb",
    "Artists": "",
    "Cover": "./cover/mixconduct-1.jpg",
    "thumbnail": "./image/mix-covers/thumbnail/mixconduct-01.jpg",
    "thumbnailLg": "./image/mix-covers/mixconduct-01-landscape.jpg",
    "id": "8",
    "date": "21 Apr 2017",
    "tracklist": ""
  },
  {
    "Title": "Mixconduct Vol 02",
    "audio": "https://hearthis.at/djg400/dj-g400-mixconduct-vol-02-audio/listen.mp3?s=Bwi",
    "Album": "Mixconduct",
    "Episode": 2,
    "color": "#fffc19",
    "hue": "",
    "popular": 2,
    "Genre": "Hip Hop, Rnb",
    "Artists": "",
    "Cover": "./cover/mixconduct-2.jpg",
    "thumbnail": "./image/mix-covers/thumbnail/mixconduct-02.jpg",
    "thumbnailLg": "./image/mix-covers/mixconduct-02-landscape.jpg",
    "id": "11",
    "date": "26 Sep 2017",
    "tracklist": ""
  },
  {
    "Title": "Hood Love 01",
    "audio": "",
    "Album": "Hood Love",
    "Episode": 1,
    "color": "#5b2831",
    "hue": "",
    "popular": 1,
    "Genre": "RnB, Rap",
    "Artists": "Ty Dolla $ign, Jhene Aiko, Ciara, Nicki Minaj, August Aulsina, Chris Brown, Kevin Gates, The Game",
    "Cover": "./cover/hood-love-01.jpg",
    "thumbnail": "./image/mix-covers/thumbnail/hoodlove-01.jpg",
    "thumbnailLg": "./image/mix-covers/hood-love-bg-lg.jpg",
    "id": "13",
    "date": "19 Feb 2018",
    "tracklist": ""
  },
  {
    "Title": "Sean Paul Mixtape",
    "audio": "",
    "Album": "Sean Paul",
    "Episode": 1,
    "color": "#330508",
    "hue": "",
    "popular": 5,
    "Genre": "Dancehall, Pop",
    "Artists": "",
    "Cover": "./cover/seanpaul.jpg",
    "thumbnail": "./image/mix-covers/thumbnail/seanpaul.jpg",
    "thumbnailLg": "./image/mix-covers/djg400-bg-lg.jpg",
    "id": "16",
    "date": "06 Oct 2018",
    "tracklist": ""
  },
  {
    "Title": "Rihanna Mixtape",
    "audio": "https://hearthis.at/djg400/dj-g400-rihanna-mixtape-audio/listen.mp3?s=u7Z",
    "Album": "Rihanna Mixtape",
    "Episode": 1,
    "color": "#ffff33",
    "hue": "",
    "popular": 1,
    "Genre": "Dancehall, Pop, House, Edm, Hip Hop",
    "Artists": "",
    "cover": "./cover/rihanna.jpg",
    "thumbnail": "./image/mix-covers/thumbnail/rihanna.jpg",
    "thumbnailLg": "./image/mix-covers/rihanna-bg-lg.jpg",
    "id": "19",
    "date": "14 Mar 2019",
    "tracklist": ""
  },
  {
    "Title": "The Shuffle Vol 01",
    "audio": "https://hearthis.at/djg400/dj-g400-the-shuffle-vol-01-audio/listen.mp3?s=FYE",
    "Album": "The Suffle",
    "Episode": 1,
    "color": "#fff",
    "hue": "",
    "popular": 1,
    "Genre": "Old School, Rap, Hip Hop, Jams",
    "Artists": "",
    "cover": "./cover/seanpaul.jpg",
    "thumbnail": "./image/mix-covers/thumbnail/shuffle-01.jpg",
    "thumbnailLg": "./image/mix-covers/djg400-bg-lg.jpg",
    "id": "18",
    "date": "03 Feb 2019",
    "tracklist": ""
  },
  {
    "Title": "Local Classics Part 01",
    "audio": "https://hearthis.at/djg400/dj-g400-local-classics-part-01-audio/listen.mp3?s=C6u",
    "Album": "Local Classics",
    "Episode": 1,
    "color": "#fff",
    "hue": "",
    "popular": 5,
    "Genre": "Kenyan Music",
    "Artists": "Calif Records, Ogopa DJs, Nonini, Jua Cali, Bamboo, Kleptomaniax, P-Unit, Bobby Mapesa, Abbas Kubaff, Calif Records",
    "Cover": "./cover/local01.jpg",
    "thumbnail": "./image/mix-covers/thumbnail/local01.jpg",
    "thumbnailLg": "./image/mix-covers/djg400-bg-lg.jpg",
    "id": "21",
    "date": "29 July 2019",
    "tracklist": ""
  },
  {
    "Title": "NTV Set 01",
    "audio": "https://hearthis.at/djg400/ntv-set-01-code-black-dj-g400/listen.mp3?s=M5x",
    "Album": "NTV",
    "Episode": 1,
    "color": "#fff",
    "hue": "filter: brightness(200%) saturate(200%);",
    "popular": 1,
    "Genre": "Keyan Hip Hop",
    "Artists": "",
    "cover": "./cover/seanpaul.jpg",
    "thumbnail": "./image/mix-covers/thumbnail/ntv-01.jpg",
    "thumbnailLg": "./image/mix-covers/ntv-04-lg.jpg",
    "id": "25",
    "date": "26 May 2020",
    "tracklist": ""
  },
  {
    "Title": "NTV Set 02",
    "audio": "https://hearthis.at/djg400/ntv-set-02-dj-g400-code-black/",
    "Album": "NTV",
    "Episode": 2,
    "color": "#fff",
    "hue": "filter: brightness(200%) saturate(200%);",
    "popular": 2,
    "Genre": "Hip Hop, Rap, Old School",
    "Artists": "",
    "cover": "./cover/seanpaul.jpg",
    "thumbnail": "./image/mix-covers/thumbnail/ntv-02.jpg",
    "thumbnailLg": "./image/mix-covers/ntv-04-lg.jpg",
    "id": "26",
    "date": "08 Jun 2020",
    "tracklist": ""
  },
  {
    "Title": "NTV Set 03",
    "audio": "https://hearthis.at/djg400/ntv-set-03-dj-g400-code-black/listen.mp3?s=hSf",
    "Album": "NTV",
    "Episode": 3,
    "color": "#fff",
    "hue": "filter: brightness(200%) saturate(200%);",
    "popular": 3,
    "Genre": "Crunk, Hip Hop",
    "Artists": "",
    "cover": "./cover/seanpaul.jpg",
    "thumbnail": "./image/mix-covers/thumbnail/ntv-03.jpg",
    "thumbnailLg": "./image/mix-covers/ntv-04-lg.jpg",
    "id": "27",
    "date": "08 Jun 2020",
    "tracklist": ""
  },
  {
    "Title": "NTV Set 04",
    "audio": "https://hearthis.at/djg400/ntv-set-04-dj-g400-code-black/listen.mp3?s=UHd",
    "Album": "NTV",
    "Episode": 4,
    "color": "#fff",
    "hue": "filter: brightness(200%) saturate(200%);",
    "popular": 4,
    "Genre": "Grime, Urban, Dancehall, Afrobeats",
    "Artists": "",
    "cover": "./cover/seanpaul.jpg",
    "thumbnail": "./image/mix-covers/thumbnail/ntv-04.jpg",
    "thumbnailLg": "./image/mix-covers/ntv-04-lg.jpg",
    "id": "28",
    "date": "08 Jul 2020",
    "tracklist": ""
  },
  {
    "Title": "Lagos To The Max 01",
    "audio": "https://hearthis.at/djg400/dj-g400-lagos-to-the-max-01/listen.mp3?s=T0W",
    "Album": "Lagos To The Max",
    "Episode": 1,
    "color": "#b7e270",
    "hue": "",
    "popular": 1,
    "Genre": "Afrobeats, Naija",
    "Artists": "Blaqbonez, Tiwa Savage, L.A.X, Burna Boy, Nana Fofie, Tems, Wizkid, Rema, Runtown",
    "Cover": "./cover/lagos01.jpg",
    "thumbnail": "./image/mix-covers/thumbnail/lagos01.jpg",
    "thumbnailLg": "./image/mix-covers/djg400-bg-lg.jpg",
    "id": "30",
    "date": "16 Sep 2022",
    "tracklist": ""
  },
  {
    "Title": "Lagos To The Max 02",
    "audio": "https://hearthis.at/djg400/dj-g400-lagos-to-the-max-02/listen.mp3?s=5Sz",
    "Album": "Lagos To The Max",
    "Episode": 2,
    "color": "#e3aa61",
    "hue": "",
    "popular": 2,
    "Genre": "Afrobeats, Naija",
    "Artists": "Wizkid, Fireboy DML, Wizkid, Darkoo, Seyi Shay, Eugy, Rema, Skepta, WSTRN, Buju, Ladipoe, Mr Eazi, ",
    "Cover": "./cover/lagos02.jpg",
    "thumbnail": "./image/mix-covers/thumbnail/lagos02.jpg",
    "thumbnailLg": "./image/mix-covers/s02.jpg",
    "id": "32",
    "date": "27 Sep 2022",
    "tracklist": ""
  },
  {
    "Title": "Lagos To The Max 03",
    "audio": "https://hearthis.at/djg400/dj-g400-lagos-to-the-max-03/listen.mp3?s=TwL",
    "Album": "Lagos To The Max",
    "Episode": 3,
    "color": "#dc6840",
    "hue": "",
    "popular": 3,
    "Genre": "Afrobeats, Naija",
    "Artists": "Oxlade, Runtown, Rema, Tems, Wizkid, Serani, Adekunle Gold, Ayra Starr, Spinal, Crayon, Ladipoe, Magixx",
    "Cover": "./cover/lagos03.jpg",
    "thumbnail": "./image/mix-covers/thumbnail/lagos03.jpg",
    "thumbnailLg": "./image/mix-covers/djg400-bg-lg.jpg",
    "id": "34",
    "date": "27 Sep 2022",
    "tracklist": ""
  },
  {
    "Title": "Lagos To The Max 04",
    "audio": "https://hearthis.at/djg400/dj-g400-lagos-to-the-max-04/listen.mp3?s=A9l",
    "Album": "Lagos To The Max",
    "Episode": 4,
    "color": "#d29f8a",
    "hue": "",
    "popular": 4,
    "Genre": "Afrobeats",
    "Artists": "Asake, Kelvyn Boy, DJ Spinal, Niniola, Falz, Maphorisa, Davido, Zinoleesky",
    "Cover": "./cover/lagos04.jpg",
    "thumbnail": "./image/mix-covers/thumbnail/lagos04.jpg",
    "thumbnailLg": "./image/mix-covers/djg400-bg-lg.jpg",
    "id": "36",
    "date": "09 Oct 2022",
    "tracklist": ""
  },
  {
    "Title": "Lagos To The Max 05",
    "audio": "https://hearthis.at/djg400/dj-g400-lagos-to-the-max-05/listen.mp3?s=klQ",
    "Album": "Lagos To The Max",
    "Episode": 5,
    "color": "#f4f4f4",
    "hue": "",
    "popular": 5,
    "Genre": "Naija",
    "Artists": "Tems, Adekunle Gold, Ayra Starr, Wizkid, Maleek Berry, Burna Boy, Tiwa Savage, Fireboy DML, Mr Eazi",
    "Cover": "./cover/lagos05.jpg",
    "thumbnail": "./image/mix-covers/thumbnail/lagos05.jpg",
    "thumbnailLg": "./image/mix-covers/djg400-bg-lg.jpg",
    "id": "38",
    "date": "20 Oct 2022",
    "tracklist": ""
  },
  {
    "Title": "Hip Hop Saved My Life 01",
    "audio": "https://hearthis.at/djg400/dj-g400-hip-hop-saved-my-life-01/listen.mp3?s=fhs",
    "Album": "Hip Hop Saved My Life ",
    "Episode": 1,
    "color": "#ffcccc",
    "hue": "",
    "popular": 1,
    "Genre": "Hip Hop, Rap, Trap",
    "Artists": "",
    "Cover": "./cover/hs01.jpg",
    "thumbnail": "./image/mix-covers/thumbnail/hhsml01.jpg",
    "thumbnailLg": "./image/mix-covers/djg400-bg-lg.jpg",
    "id": "29",
    "date": "16 Sep 2022",
    "tracklist": ""
  },
  {
    "Title": "Hip Hop Saved My Life 02",
    "audio": "https://hearthis.at/djg400/dj-g400-hip-hop-saved-my-life-02/listen.mp3?s=AOp",
    "Album": "Hip Hop Saved My Life ",
    "Episode": 2,
    "color": "#e08532",
    "hue": "",
    "popular": 2,
    "Genre": "Hip Hop",
    "Artists": "Blxst",
    "Cover": "./cover/hs01.jpg",
    "thumbnail": "./image/mix-covers/thumbnail/hhsml02.jpg",
    "thumbnailLg": "./image/mix-covers/djg400-bg-lg.jpg",
    "id": "31",
    "date": "27 Sep 2022",
    "tracklist": ""
  },
  {
    "Title": "Hip Hop Saved My Life 03",
    "audio": "https://hearthis.at/djg400/dj-g400-hip-hop-saved-my-life-03/listen.mp3?s=5PJ",
    "Album": "Hip Hop Saved My Life",
    "Episode": 3,
    "color": "#39ffba",
    "hue": "",
    "popular": 3,
    "Genre": "Hip Hop, RnB",
    "Artists": "Blxst, Chris Brown, Ty Dolla $ign, Pop Smoke, WSTRN, Roddy Rich, Tinashe, Drake, Teflii, The Game",
    "Cover": "./cover/hs01.jpg",
    "thumbnail": "./image/mix-covers/thumbnail/hhsml03.jpg",
    "thumbnailLg": "./image/mix-covers/hhsml03-bg-lg.jpg",
    "id": "33",
    "date": "04 Oct 2022",
    "tracklist": ""
  },
  {
    "Title": "Hip Hop Saved My Life 04",
    "audio": "https://hearthis.at/djg400/dj-g400-hip-hop-saved-my-life-04/listen.mp3?s=z42",
    "Album": "Hip Hop Saved My Life ",
    "Episode": 4,
    "color": "#23cba3",
    "hue": "",
    "popular": 4,
    "Genre": "Trap, UK",
    "Artists": "21 Savage, Lil Uzi Vert, Skepta, Dae Dae, Dreezy, Dej Loaf, Nicki Minaj, Yo Gotti, Lil Mosey, Travis Scott, MIA, Future, YG, Asap Rocky, Kodak Black, French Montana, TK N Cash, Dababy, Smokepurpp, Nav, Lil Bibby, Playboi Carti",
    "Cover": "./cover/hs01.jpg",
    "thumbnail": "./image/mix-covers/thumbnail/hhsml04.jpg",
    "thumbnailLg": "./image/mix-covers/djg400-bg-lg.jpg",
    "id": "35",
    "similar": "1, 6, 10, 14, 17, 23, 24, ",
    "date": "14 Oct 2022",
    "tracklist": ""
  },
  {
    "Title": "Hip Hop Saved My Life 05",
    "audio": "https://hearthis.at/djg400/dj-g400-hip-hop-saved-my-life-05/listen.mp3?s=Mxv",
    "Album": "Hip Hop Saved My Life",
    "Episode": 5,
    "color": "#f4f4f4",
    "hue": "",
    "popular": 5,
    "Genre": "Trap",
    "Artists": "Trouble, Boosie Badazz, Playboi Carti, City Girls, Big Sean, Post Malone, Drake, Skepta, Young Bleu",
    "Cover": "./cover/hs01.jpg",
    "thumbnail": "./image/mix-covers/thumbnail/hhsml05.jpg",
    "thumbnailLg": "./image/mix-covers/djg400-bg-lg.jpg",
    "id": "37",
    "similar": "1, 6, 10, 14, 17, 23, 24, ",
    "date": "26 Oct 2022",
    "tracklist": ""
  },
  {
    "Title": "Local Classics 02",
    "audio": "https://hearthis.at/djg400/dj-g400-local-classics-part-01-audio/listen.mp3?s=C6u",
    "Album": "Local Classics",
    "Episode": 2,
    "color": "#f4f4f4",
    "hue": "",
    "popular": 2,
    "Genre": "Kenyan Music",
    "Artists": "Sauti Sol, Nonini, Jua Cali, Bamboo, Kleptomaniax, P-Unit, Bobby Mapesa, Abbas Kubaff, Calif Records",
    "Cover": "./cover/local02.jpg",
    "thumbnail": "./image/mix-covers/thumbnail/local02.jpg",
    "thumbnailLg": "./image/mix-covers/djg400-bg-lg.jpg",
    "id": "40",
    "date": "01 Oct 23",
    "tracklist": ""
  }
]
